Metadata-Version: 2.4
Name: mclang
Version: 1.1.3
Summary: Read and write to .lang files.
Home-page: https://github.com/legopitstop/mclang/
Author: Legopitstop
Author-email: contact@lpsmods.dev
License: MIT
Project-URL: Download, https://github.com/legopitstop/mclang/releases
Project-URL: Documentation, https://docs.lpsmods.dev/mclang
Project-URL: Source Code, https://github.com/legopitstop/mclang/
Keywords: Minecraft: Bedrock Edition,lang,language,translate
Classifier: Development Status :: 5 - Production/Stable
Classifier: Intended Audience :: Developers
Classifier: License :: OSI Approved :: MIT License
Classifier: Programming Language :: Python :: 3.9
Classifier: Programming Language :: Python :: 3.10
Classifier: Programming Language :: Python :: 3.11
Classifier: Programming Language :: Python :: 3.12
Classifier: Programming Language :: Python :: 3.13
Classifier: Topic :: File Formats
Classifier: Typing :: Typed
Requires-Python: >=3.9
License-File: LICENSE
Requires-Dist: deep-translator
Provides-Extra: testing
Requires-Dist: pytest>=6.0; extra == "testing"
Requires-Dist: pytest-cov>=2.0; extra == "testing"
Requires-Dist: mypy>=1.11.2; extra == "testing"
Requires-Dist: flake8>=3.9; extra == "testing"
Requires-Dist: tox>=3.24; extra == "testing"
Dynamic: license-file
